[
  {
    "id": 1,
    "title": "HP EliteBook 840 G8 Core i7-1165G7 16GB RAM 512GB SSD 14\" FHD",
    "price": 549,
    "category": "HP",
    "rating": 4.8,
    "image": "/products/Product One.jpeg",
    "badge": "New"
  },
  {
    "id": 2,
    "title": "HP ProBook 450 G9 Core i5-1235U 8GB RAM 256GB SSD 15.6\" FHD",
    "price": 499,
    "category": "HP",
    "rating": 4.5,
    "image": "/products/Product Two.jpeg",
    "badge": ""
  },
  {
    "id": 3,
    "title": "HP Pavilion Laptop 15 Core i7-1355U 16GB RAM 1TB SSD 15.6\" Touch",
    "price": 680,
    "category": "HP",
    "rating": 4.6,
    "image": "/products/Product Three.jpeg",
    "badge": "New"
  },
  {
    "id": 4,
    "title": "HP ZBook Firefly G10 Core i7-1365U 32GB RAM 1TB SSD 14\" Workstation",
    "price": 1250,
    "category": "HP",
    "rating": 4.9,
    "image": "/products/Product Four.jpeg",
    "badge": ""
  },
  {
    "id": 5,
    "title": "HP Envy x360 2-in-1 Ryzen 7 7730U 16GB RAM 512GB SSD 15.6\" Touch",
    "price": 720,
    "category": "HP",
    "rating": 4.7,
    "image": "/products/Product Five.jpeg",
    "badge": "New"
  },
  {
    "id": 6,
    "title": "ASUS ROG Zephyrus G14 Ryzen 9 RTX 4060 16GB RAM 1TB SSD",
    "price": 1450,
    "category": "Gaming",
    "rating": 4.9,
    "image": "/products/Product Six.jpeg",
    "badge": ""
  },
  {
    "id": 7,
    "title": "MSI Katana 15 Core i7-13620H RTX 4050 16GB RAM 1TB SSD 144Hz",
    "price": 999,
    "category": "Gaming",
    "rating": 4.4,
    "image": "/products/Product Seven.jpeg",
    "badge": "Sale"
  },
  {
    "id": 8,
    "title": "Lenovo Legion Slim 5 Gen 8 Ryzen 7 RTX 4070 16GB RAM 512GB SSD",
    "price": 1299,
    "category": "Gaming",
    "rating": 4.8,
    "image": "/products/Product Eight.jpeg",
    "badge": ""
  },
  {
    "id": 9,
    "title": "Acer Predator Helios Neo 16 Core i7 RTX 4060 16GB RAM 1TB SSD",
    "price": 1150,
    "category": "Gaming",
    "rating": 4.7,
    "image": "/products/Product Nine.jpeg",
    "badge": ""
  },
  {
    "id": 10,
    "title": "Razer Blade 15 Core i7-13800H RTX 4070 16GB RAM 1TB SSD QHD",
    "price": 2399,
    "category": "Gaming",
    "rating": 4.9,
    "image": "/products/Product Ten.jpeg",
    "badge": "New"
  }
]
